optcat/__init__.py
optcat/core.py
optcat-0.1.0.dist-info/LICENSE
optcat-0.1.0.dist-info/WHEEL
optcat-0.1.0.dist-info/METADATA
optcat-0.1.0.dist-info/RECORD
