Metadata-Version: 2.1
Name: optcat
Version: 0.1.0
Summary: OptCAT (= Optuna + CatBoost) provides a scikit-learn compatible estimator that tunes hyperparameters in CatBoost with Optuna.
Home-page: https://github.com/wakamezake/OptCAT
License: MIT
Keywords: catboost,optuna,hyperparameter tuning
Author: wakame1367
Author-email: hotwater1367@gmail.com
Requires-Python: >=3.6.1
Classifier: License :: OSI Approved :: MIT License
Classifier: Programming Language :: Python :: 3
Classifier: Programming Language :: Python :: 3.7
Classifier: Programming Language :: Python :: 3.8
Requires-Dist: catboost (>=0.22,<0.23)
Requires-Dist: optuna (>=1.2.0,<2.0.0)
Requires-Dist: pandas (>=1.0.2,<2.0.0)
Requires-Dist: scikit-learn (>=0.22.2,<0.23.0)
Project-URL: Repository, https://github.com/wakamezake/OptCAT
